{
    "_config_name": "spambot.settings",
    "spambot_criteria_email": "SPAMBOT_DEFAULT_CRITERIA_EMAIL",
    "spambot_criteria_username": "SPAMBOT_DEFAULT_CRITERIA_USERNAME",
    "spambot_criteria_ip": "SPAMBOT_DEFAULT_CRITERIA_IP",
    "spambot_whitelist_email": "",
    "spambot_whitelist_username": "",
    "spambot_whitelist_ip": "",
    "spambot_user_register_protect": true,
    "spambot_blacklisted_delay": "SPAMBOT_DEFAULT_DELAY",
    "spambot_cron_user_limit": "SPAMBOT_DEFAULT_CRON_USER_LIMIT",
    "spambot_check_blocked_accounts": false,
    "spambot_spam_account_action": "SPAMBOT_ACTION_NONE",
    "spambot_spam_account_nodes_action": "SPAMBOT_ACTION_NONE",
    "spambot_last_checked_uid": "0",
    "spambot_blocked_message_email": "SPAMBOT_DEFAULT_BLOCKED_MESSAGE",
    "spambot_blocked_message_username": "SPAMBOT_DEFAULT_BLOCKED_MESSAGE",
    "spambot_blocked_message_ip": "SPAMBOT_DEFAULT_BLOCKED_MESSAGE",
    "spambot_log_blocked_registration": true,
    "spambot_sfs_api_key": false,
    "spambot_enable_cache": true,
    "spambot_cache_expire": "CACHE_PERMANENT",
    "spambot_cache_expire_false": "300",
    "spambot_blocked_message": false
}